taxapex/__init__.py
taxapex/client.py
taxapex/models.py
taxapex-1.0.1.dist-info/METADATA
taxapex-1.0.1.dist-info/WHEEL
taxapex-1.0.1.dist-info/top_level.txt
taxapex-1.0.1.dist-info/RECORD
